llama_index/postprocessor/contextual_rerank/__init__.py
llama_index/postprocessor/contextual_rerank/base.py
llama_index_postprocessor_contextual_rerank-0.2.1.dist-info/METADATA
llama_index_postprocessor_contextual_rerank-0.2.1.dist-info/WHEEL
llama_index_postprocessor_contextual_rerank-0.2.1.dist-info/licenses/LICENSE
llama_index_postprocessor_contextual_rerank-0.2.1.dist-info/RECORD
