Metadata-Version: 2.4
Name: llama-index-postprocessor-contextual-rerank
Version: 0.2.1
Summary: llama-index postprocessor contextual rerank integration
Author-email: Sean Smith <sean.smith@contextual.ai>
License-Expression: MIT
License-File: LICENSE
Requires-Python: <4.0,>=3.9
Requires-Dist: contextual-client<0.5,>=0.4.0
Requires-Dist: llama-index-core<0.15,>=0.13.0
